cornet/__init__.py
cornet/dict_utils.py
cornet/main.py
cornet/sqoop_cmd.py
cornet/task_config.py
cornet/connectors/__init__.py
cornet/connectors/base_connector.py
cornet/connectors/mysql_connector.py
cornet/connectors/postgresql_connector.py
cornet-0.1rc1.dist-info/DESCRIPTION.rst
cornet-0.1rc1.dist-info/entry_points.txt
cornet-0.1rc1.dist-info/METADATA
cornet-0.1rc1.dist-info/metadata.json
cornet-0.1rc1.dist-info/RECORD
cornet-0.1rc1.dist-info/top_level.txt
cornet-0.1rc1.dist-info/WHEEL
