Metadata-Version: 2.0
Name: cornet
Version: 0.1rc1
Summary: Easily generate Apache Sqoop commands based on YAML config file
Home-page: https://github.com/datadudes/cornet
Author: Marcel Krcah, Daan Debie
Author-email: marcel.krcah@gmail.com, debie.daan@gmail.com
License: MIT
Keywords: sqoop yaml hadoop hive mysql postgresql
Platform: UNKNOWN
Classifier: Development Status :: 4 - Beta
Classifier: Environment :: Console
Classifier: Intended Audience :: Developers
Classifier: License :: OSI Approved :: MIT License
Classifier: Operating System :: POSIX
Classifier: Operating System :: MacOS
Classifier: Operating System :: Unix
Classifier: Programming Language :: Python
Classifier: Programming Language :: Python :: 2
Classifier: Topic :: Database
Classifier: Topic :: Utilities
Requires-Dist: Jinja2 (==2.7.3)
Requires-Dist: PyYAML (==3.11)
Requires-Dist: click (==3.3)
Provides-Extra: postgres
Requires-Dist: psycopg2 (==2.6); extra == 'postgres'
Provides-Extra: mysql
Requires-Dist: mysqlclient (==1.3.5); extra == 'mysql'
